fhwise/__init__.py
fhwise/protocol.py
fhwise/version.py
py_fhwise-0.0.4.dist-info/METADATA
py_fhwise-0.0.4.dist-info/WHEEL
py_fhwise-0.0.4.dist-info/top_level.txt
py_fhwise-0.0.4.dist-info/RECORD
