Metadata-Version: 2.1
Name: py-fhwise
Version: 0.0.4
Summary: Control fhwise player though UDP socket
Home-page: https://github.com/smarthomefans/py-fhwise
Author: SchumyHao
Author-email: schumy.haojl@gmail.com
License: MIT
Project-URL: Bug Reports, https://github.com/smarthomefans/py-fhwise/issues/
Project-URL: Source, https://github.com/smarthomefans/py-fhwise/
Keywords: fhwise smarthome music-player player
Platform: UNKNOWN
Requires-Python: >=3.5
Requires-Dist: construct
